mdpydoc/__init__.py
mdpydoc/ast_parser.py
mdpydoc/cli.py
mdpydoc/doc_generator.py
mdpydoc/docstring_parser.py
mdpydoc/file_processor.py
mdpydoc/logger.py
mdpydoc/markdown_generator.py
mdpydoc-0.2.5.dist-info/LICENSE
mdpydoc-0.2.5.dist-info/METADATA
mdpydoc-0.2.5.dist-info/WHEEL
mdpydoc-0.2.5.dist-info/entry_points.txt
mdpydoc-0.2.5.dist-info/top_level.txt
mdpydoc-0.2.5.dist-info/RECORD
